[
    {
        "sehir": "İstanbul",
        "sicaklik": 23.9,
        "hissedilen": 25.9,
        "nem": 76,
        "ruzgar": 10.4,
        "guncelleme": "20.07.2026 19:42"
    },
    {
        "sehir": "Ankara",
        "sicaklik": 25.7,
        "hissedilen": 26.6,
        "nem": 46,
        "ruzgar": 1.1,
        "guncelleme": "20.07.2026 19:42"
    },
    {
        "sehir": "İzmir",
        "sicaklik": 30.4,
        "hissedilen": 31.5,
        "nem": 38,
        "ruzgar": 2.6,
        "guncelleme": "20.07.2026 19:42"
    },
    {
        "sehir": "Gaziantep",
        "sicaklik": 28.7,
        "hissedilen": 28.8,
        "nem": 46,
        "ruzgar": 13.6,
        "guncelleme": "20.07.2026 19:42"
    }
]