[
    {
        "sehir": "İstanbul",
        "sicaklik": 23.7,
        "hissedilen": 24.8,
        "nem": 71,
        "ruzgar": 12.1,
        "guncelleme": "13.07.2026 18:19"
    },
    {
        "sehir": "Ankara",
        "sicaklik": 25.5,
        "hissedilen": 24.8,
        "nem": 45,
        "ruzgar": 10.5,
        "guncelleme": "13.07.2026 18:19"
    },
    {
        "sehir": "İzmir",
        "sicaklik": 29.5,
        "hissedilen": 30.9,
        "nem": 45,
        "ruzgar": 4.8,
        "guncelleme": "13.07.2026 18:19"
    },
    {
        "sehir": "Gaziantep",
        "sicaklik": 27.8,
        "hissedilen": 27.8,
        "nem": 46,
        "ruzgar": 12.1,
        "guncelleme": "13.07.2026 18:19"
    }
]